{
  "code": "buick",
  "name": "Buick",
  "brandColor": "#002d5c",
  "styles": {
    "primary": {
      "label": "Primary",
      "backgroundColor": "#002d5c",
      "textColor": "#ffffff",
      "hoverBackgroundColor": "#ffffff",
      "hoverTextColor": "#002d5c",
      "borderColor": "#002d5c",
      "borderRadius": "4px",
      "textTransform": "uppercase",
      "fontSize": "16px",
      "fontWeight": "bold",
      "padding": "11px",
      "marginTop": "6px",
      "marginBottom": "0px",
      "letterSpacing": "0.1em",
      "borderWidth": "2px",
      "transition": "all 0.3s ease"
    },
    "secondary": {
      "label": "Secondary",
      "backgroundColor": "transparent",
      "textColor": "#002d5c",
      "hoverBackgroundColor": "#002d5c",
      "hoverTextColor": "#ffffff",
      "borderColor": "#002d5c",
      "borderRadius": "4px",
      "textTransform": "uppercase",
      "fontSize": "16px",
      "fontWeight": "bold",
      "padding": "11px",
      "marginTop": "6px",
      "marginBottom": "0px",
      "letterSpacing": "0.1em",
      "borderWidth": "2px",
      "transition": "all 0.3s ease"
    },
    "inverse": {
      "label": "Inverse",
      "backgroundColor": "#ffffff",
      "textColor": "#002d5c",
      "hoverBackgroundColor": "#002d5c",
      "hoverTextColor": "#ffffff",
      "borderColor": "#ffffff",
      "borderRadius": "4px",
      "textTransform": "uppercase",
      "fontSize": "16px",
      "fontWeight": "bold",
      "padding": "11px",
      "marginTop": "6px",
      "marginBottom": "0px",
      "letterSpacing": "0.1em",
      "borderWidth": "2px",
      "transition": "all 0.3s ease"
    },
    "dark": {
      "label": "Dark",
      "backgroundColor": "#000000",
      "textColor": "#ffffff",
      "hoverBackgroundColor": "#002d5c",
      "hoverTextColor": "#ffffff",
      "borderColor": "#000000",
      "borderRadius": "4px",
      "textTransform": "uppercase",
      "fontSize": "16px",
      "fontWeight": "bold",
      "padding": "11px",
      "marginTop": "6px",
      "marginBottom": "0px",
      "letterSpacing": "0.1em",
      "borderWidth": "2px",
      "transition": "all 0.3s ease"
    },
    "light": {
      "label": "Light",
      "backgroundColor": "#ffffff",
      "textColor": "#002d5c",
      "hoverBackgroundColor": "#002d5c",
      "hoverTextColor": "#ffffff",
      "borderColor": "#002d5c",
      "borderRadius": "4px",
      "textTransform": "uppercase",
      "fontSize": "16px",
      "fontWeight": "bold",
      "padding": "11px",
      "marginTop": "6px",
      "marginBottom": "0px",
      "letterSpacing": "0.1em",
      "borderWidth": "2px",
      "transition": "all 0.3s ease"
    },
    "ghost": {
      "label": "Ghost",
      "backgroundColor": "transparent",
      "textColor": "#ffffff",
      "hoverBackgroundColor": "#ffffff",
      "hoverTextColor": "#002d5c",
      "borderColor": "#ffffff",
      "borderRadius": "4px",
      "textTransform": "uppercase",
      "fontSize": "16px",
      "fontWeight": "bold",
      "padding": "11px",
      "marginTop": "6px",
      "marginBottom": "0px",
      "letterSpacing": "0.1em",
      "borderWidth": "2px",
      "transition": "all 0.3s ease"
    },
    "accent": {
      "label": "Accent",
      "backgroundColor": "#002d5c",
      "textColor": "#ffffff",
      "hoverBackgroundColor": "#ffffff",
      "hoverTextColor": "#000000",
      "borderColor": "#002d5c",
      "borderRadius": "4px",
      "textTransform": "uppercase",
      "fontSize": "16px",
      "fontWeight": "bold",
      "padding": "11px",
      "marginTop": "6px",
      "marginBottom": "0px",
      "letterSpacing": "0.1em",
      "borderWidth": "2px",
      "transition": "all 0.3s ease"
    }
  },
  "font": null
}
