{
  "code": "ford",
  "name": "Ford",
  "brandColor": "#00095B",
  "styles": {
    "primary": {
      "label": "Primary",
      "backgroundColor": "#00095B",
      "textColor": "#ffffff",
      "hoverBackgroundColor": "#ffffff",
      "hoverTextColor": "#00095B",
      "borderColor": "#00095B",
      "borderRadius": "4px",
      "textTransform": "uppercase",
      "fontSize": "16px",
      "fontWeight": "bold",
      "padding": "11px",
      "marginTop": "6px",
      "marginBottom": "0px",
      "letterSpacing": "0.1em",
      "borderWidth": "2px",
      "transition": "all 0.3s ease"
    },
    "secondary": {
      "label": "Secondary",
      "backgroundColor": "transparent",
      "textColor": "#00095B",
      "hoverBackgroundColor": "#00095B",
      "hoverTextColor": "#ffffff",
      "borderColor": "#00095B",
      "borderRadius": "4px",
      "textTransform": "uppercase",
      "fontSize": "16px",
      "fontWeight": "bold",
      "padding": "11px",
      "marginTop": "6px",
      "marginBottom": "0px",
      "letterSpacing": "0.1em",
      "borderWidth": "2px",
      "transition": "all 0.3s ease"
    },
    "lincolnDark": {
      "label": "Lincoln Dark",
      "backgroundColor": "#22292b",
      "textColor": "#ffffff",
      "hoverBackgroundColor": "#485B65",
      "hoverTextColor": "#ffffff",
      "borderColor": "#22292b",
      "borderRadius": "4px",
      "textTransform": "uppercase",
      "fontSize": "16px",
      "fontWeight": "bold",
      "padding": "11px",
      "marginTop": "6px",
      "marginBottom": "0px",
      "letterSpacing": "0.1em",
      "borderWidth": "2px",
      "transition": "all 0.3s ease"
    },
    "lincolnGrey": {
      "label": "Lincoln Grey",
      "backgroundColor": "#485B65",
      "textColor": "#ffffff",
      "hoverBackgroundColor": "#22292b",
      "hoverTextColor": "#ffffff",
      "borderColor": "#485B65",
      "borderRadius": "4px",
      "textTransform": "uppercase",
      "fontSize": "16px",
      "fontWeight": "bold",
      "padding": "11px",
      "marginTop": "6px",
      "marginBottom": "0px",
      "letterSpacing": "0.1em",
      "borderWidth": "2px",
      "transition": "all 0.3s ease"
    },
    "whiteOutline": {
      "label": "White Outline",
      "backgroundColor": "transparent",
      "textColor": "#ffffff",
      "hoverBackgroundColor": "#ffffff",
      "hoverTextColor": "#00095B",
      "borderColor": "#ffffff",
      "borderRadius": "4px",
      "textTransform": "uppercase",
      "fontSize": "16px",
      "fontWeight": "bold",
      "padding": "11px",
      "marginTop": "6px",
      "marginBottom": "0px",
      "letterSpacing": "0.1em",
      "borderWidth": "2px",
      "transition": "all 0.3s ease"
    },
    "lincolnOutline": {
      "label": "Lincoln Outline",
      "backgroundColor": "transparent",
      "textColor": "#485B65",
      "hoverBackgroundColor": "#485B65",
      "hoverTextColor": "#ffffff",
      "borderColor": "#485B65",
      "borderRadius": "4px",
      "textTransform": "uppercase",
      "fontSize": "16px",
      "fontWeight": "bold",
      "padding": "11px",
      "marginTop": "6px",
      "marginBottom": "0px",
      "letterSpacing": "0.1em",
      "borderWidth": "2px",
      "transition": "all 0.3s ease"
    },
    "lightOnDark": {
      "label": "Light on Dark",
      "backgroundColor": "#ffffff",
      "textColor": "#00095B",
      "hoverBackgroundColor": "#00095B",
      "hoverTextColor": "#ffffff",
      "borderColor": "#ffffff",
      "borderRadius": "4px",
      "textTransform": "uppercase",
      "fontSize": "16px",
      "fontWeight": "bold",
      "padding": "11px",
      "marginTop": "6px",
      "marginBottom": "0px",
      "letterSpacing": "0.1em",
      "borderWidth": "2px",
      "transition": "all 0.3s ease"
    }
  },
  "font": null
}
